BatJiqiXuexiMianshi1000TiXilieDi1325Ti/README.md
BatJiqiXuexiMianshi1000TiXilieDi1325Ti/__init__.py
BatJiqiXuexiMianshi1000TiXilieDi1325Ti/__main__.py
BatJiqiXuexiMianshi1000TiXilieDi1325Ti/file.pdf
BatJiqiXuexiMianshi1000TiXilieDi1325Ti/index.html
bat_jiqi_xuexi_mianshi_1000_ti_xilie_di_1_325_ti-2024.3.4.0.dist-info/METADATA
bat_jiqi_xuexi_mianshi_1000_ti_xilie_di_1_325_ti-2024.3.4.0.dist-info/WHEEL
bat_jiqi_xuexi_mianshi_1000_ti_xilie_di_1_325_ti-2024.3.4.0.dist-info/entry_points.txt
bat_jiqi_xuexi_mianshi_1000_ti_xilie_di_1_325_ti-2024.3.4.0.dist-info/top_level.txt
bat_jiqi_xuexi_mianshi_1000_ti_xilie_di_1_325_ti-2024.3.4.0.dist-info/RECORD
